bullish/__init__.py
bullish/analysis/__init__.py
bullish/analysis/analysis.py
bullish/analysis/backtest.py
bullish/analysis/constants.py
bullish/analysis/filter.py
bullish/analysis/functions.py
bullish/analysis/indicators.py
bullish/analysis/industry_views.py
bullish/analysis/openai.py
bullish/analysis/portfolio.py
bullish/analysis/predefined_filters.py
bullish/app/__init__.py
bullish/app/app.py
bullish/cli.py
bullish/database/__init__.py
bullish/database/alembic/README
bullish/database/alembic/alembic.ini
bullish/database/alembic/env.py
bullish/database/alembic/script.py.mako
bullish/database/alembic/versions/037dbd721317_.py
bullish/database/alembic/versions/040b15fba458_.py
bullish/database/alembic/versions/048bac60974f_.py
bullish/database/alembic/versions/08ac1116e055_.py
bullish/database/alembic/versions/11d35a452b40_.py
bullish/database/alembic/versions/12889a2cbd7d_.py
bullish/database/alembic/versions/14b821135552_.py
bullish/database/alembic/versions/17e51420e7ad_.py
bullish/database/alembic/versions/260fcff7212e_.py
bullish/database/alembic/versions/49c83f9eb5ac_.py
bullish/database/alembic/versions/4b0a2f40b7d3_.py
bullish/database/alembic/versions/4ee82b171449_.py
bullish/database/alembic/versions/5b10ee7604c1_.py
bullish/database/alembic/versions/65662e214031_.py
bullish/database/alembic/versions/660897c02c00_.py
bullish/database/alembic/versions/6d252e23f543_.py
bullish/database/alembic/versions/73564b60fe24_.py
bullish/database/alembic/versions/79bc71ec6f9e_.py
bullish/database/alembic/versions/ae444f338124_.py
bullish/database/alembic/versions/b36c310f49ec_.py
bullish/database/alembic/versions/b76079e9845f_.py
bullish/database/alembic/versions/bf6b86dd5463_.py
bullish/database/alembic/versions/c06dc04e782b_.py
bullish/database/alembic/versions/c828e29e1105_.py
bullish/database/alembic/versions/cc28171c21a4_.py
bullish/database/alembic/versions/d0e58e050845_.py
bullish/database/alembic/versions/d663166c531d_.py
bullishpy-0.85.0.dist-info/METADATA
bullishpy-0.85.0.dist-info/WHEEL
bullishpy-0.85.0.dist-info/entry_points.txt
bullishpy-0.85.0.dist-info/licenses/LICENSE
bullishpy-0.85.0.dist-info/RECORD
