Metadata-Version: 2.4
Name: bullishpy
Version: 0.85.0
Summary: 
License-File: LICENSE
Author: aan
Author-email: andoludovic.andriamamonjy@gmail.com
Requires-Python: >=3.12,<3.13
Classifier: Programming Language :: Python :: 3
Classifier: Programming Language :: Python :: 3.12
Requires-Dist: bearishpy (>=0.43.0,<1.0.0)
Requires-Dist: click (>=7.0,<=8.1)
Requires-Dist: huey (>=2.5.3,<3.0.0)
Requires-Dist: joblib (>=1.5.1,<2.0.0)
Requires-Dist: myportfolio (>=0.6.0,<1.0.0)
Requires-Dist: mysec (>=0.8.0,<1.0.0)
Requires-Dist: pandas-ta (>=0.4.71b0,<0.5.0)
Requires-Dist: plotly (>=4.12.0,<6.0.0)
Requires-Dist: streamlit (>=1.45.1,<2.0.0)
Requires-Dist: streamlit-file-browser (>=3.2.22,<4.0.0)
Requires-Dist: streamlit-pydantic (>=v0.6.1-rc.3,<0.7.0)
Requires-Dist: ta-lib (>=0.6.4,<0.7.0)
Requires-Dist: tickermood (>=0.29.0,<0.30.0)
Requires-Dist: vectorbt (>=0.28.0,<0.29.0)
